Metadata-Version: 1.0
Name: covid-reports
Version: 0.1
Summary: covid-19 daily data
Home-page: https://github.com/OpenJarbas/covid_reports
Author: jarbasAI
Author-email: jarbasai@mailfence.com
License: MIT
Platform: UNKNOWN
